{
  "total": 9,
  "image_info": [
    {
      "name": 1,
      "author": 1,
      "pid": 1
    },
    {
      "name": 2,
      "author": 2,
      "pid": 2
    },
    {
      "name": 3,
      "author": 3,
      "pid": 3
    },
    {
      "name": 4,
      "author": 4,
      "pid": 4
    },
    {
      "name": 5,
      "author": 5,
      "pid": 5
    },
    {
      "name": 6,
      "author": 6,
      "pid": 6
    },
    {
      "name": 7,
      "author": 7,
      "pid": 7
    },
    {
      "name": 8,
      "author": 8,
      "pid": 8
    },
    {
      "name": 9,
      "author": 9,
      "pid": 9
    }
  ]
}
